{
  "kind": "collectionType",
  "collectionName": "events",
  "info": {
    "singularName": "event",
    "pluralName": "events",
    "displayName": "Events",
    "description": ""
  },
  "options": {
    "draftAndPublish": true
  },
  "pluginOptions": {},
  "attributes": {
    "eventOrganizer": {
      "type": "email"
    },
    "eventName": {
      "type": "string"
    },
    "eventMode": {
      "type": "enumeration",
      "enum": [
        "video",
        "audio",
        "hybrid"
      ]
    },
    "eventDateAndTime": {
      "type": "datetime"
    },
    "eventSpeakers": {
      "type": "json"
    },
    "eventDescription": {
      "type": "text"
    },
    "eventCover": {
      "allowedTypes": [
        "images",
        "files",
        "videos",
        "audios"
      ],
      "type": "media",
      "multiple": false
    },
    "eventAttendees": {
      "type": "json"
    }
  }
}
